afpdb/__init__.py
afpdb/afpdb.py
afpdb/aiparser.py
afpdb/antibody.py
afpdb/mol3D.py
afpdb/mypymol.py
afpdb/pdbinfo.py
afpdb/pymol3D.py
afpdb/structure_metrics.py
afpdb/thread_seq.py
afpdb/util.py
afpdb/myalphafold/__init__.py
afpdb/myalphafold/common/protein.py
afpdb/myalphafold/common/residue_constants.py
afpdb/mycolabdesign/__init__.py
afpdb/mycolabdesign/getpdb.py
afpdb/mycolabdesign/protein.py
afpdb/mycolabdesign/utils.py
afpdb/mycolabfold/__init__.py
afpdb/mycolabfold/utils.py
afpdb-0.3.1.dist-info/licenses/LICENSE
afpdb-0.3.1.dist-info/METADATA
afpdb-0.3.1.dist-info/WHEEL
afpdb-0.3.1.dist-info/top_level.txt
afpdb-0.3.1.dist-info/RECORD
