Metadata-Version: 2.4
Name: afpdb
Version: 0.3.1
Summary: A Numpy-based PDB structure manipulation package
Home-page: https://github.com/data2code/afpdb
Author: Yingyao Zhou
Author-email: yingyao.zhou@novartis.com
License: MIT
Project-URL: homepage, https://github.com/data2code/afpdb
Project-URL: documentation, https://github.com/data2code/afpdb/tutorial
Project-URL: issues, https://github.com/data2code/afpdb/issues
Classifier: Development Status :: 5 - Production/Stable
Classifier: Intended Audience :: Science/Research
Classifier: License :: OSI Approved :: MIT License
Classifier: Operating System :: POSIX :: Linux
Classifier: Programming Language :: Python :: 3.7
Requires-Python: >=3.7
License-File: LICENSE
Requires-Dist: pandas
Requires-Dist: numpy
Requires-Dist: scipy
Requires-Dist: biopython
Requires-Dist: dm-tree
Requires-Dist: py3Dmol
Requires-Dist: tabulate
Requires-Dist: requests
Dynamic: author
Dynamic: author-email
Dynamic: classifier
Dynamic: home-page
Dynamic: license
Dynamic: license-file
Dynamic: requires-dist
Dynamic: requires-python
Dynamic: summary
